aws_text_insight/.DS_Store
aws_text_insight/__init__.py
aws_text_insight/_version.py
aws_text_insight/__pycache__/__init__.cpython-38.pyc
aws_text_insight/__pycache__/_version.cpython-38.pyc
aws_text_insight/docs/__init__.py
aws_text_insight/docs/__pycache__/__init__.cpython-38.pyc
aws_text_insight/lbd/.DS_Store
aws_text_insight/lbd/__init__.py
aws_text_insight/lbd/hdl_hello_world.py
aws_text_insight/lbd/__pycache__/__init__.cpython-38.pyc
aws_text_insight/lbd/__pycache__/hdl_hello_world.cpython-38.pyc
aws_text_insight-0.0.1.dist-info/AUTHORS.rst
aws_text_insight-0.0.1.dist-info/LICENSE.txt
aws_text_insight-0.0.1.dist-info/METADATA
aws_text_insight-0.0.1.dist-info/WHEEL
aws_text_insight-0.0.1.dist-info/top_level.txt
aws_text_insight-0.0.1.dist-info/RECORD
